LICENSE
MANIFEST.in
README.md
setup.py
salesforce_api/__init__.py
salesforce_api/client.py
salesforce_api/config.py
salesforce_api/core.py
salesforce_api/exceptions.py
salesforce_api/login.py
salesforce_api.egg-info/PKG-INFO
salesforce_api.egg-info/SOURCES.txt
salesforce_api.egg-info/dependency_links.txt
salesforce_api.egg-info/requires.txt
salesforce_api.egg-info/top_level.txt
salesforce_api.egg-info/zip-safe
salesforce_api/const/__init__.py
salesforce_api/const/misc.py
salesforce_api/const/service.py
salesforce_api/const/status.py
salesforce_api/const/test.py
salesforce_api/const/type.py
salesforce_api/data/soap_messages/deploy/cancel.msg
salesforce_api/data/soap_messages/deploy/deploy.msg
salesforce_api/data/soap_messages/deploy/status.msg
salesforce_api/data/soap_messages/login/login.msg
salesforce_api/data/soap_messages/retrieve/retrieve.msg
salesforce_api/data/soap_messages/retrieve/status.msg
salesforce_api/models/__init__.py
salesforce_api/models/base.py
salesforce_api/models/bulk.py
salesforce_api/models/deploy.py
salesforce_api/models/retrieve.py
salesforce_api/models/shared.py
salesforce_api/models/tooling.py
salesforce_api/services/__init__.py
salesforce_api/services/base.py
salesforce_api/services/basic.py
salesforce_api/services/deploy.py
salesforce_api/services/retrieve.py
salesforce_api/services/sobjects.py
salesforce_api/services/tooling.py
salesforce_api/services/bulk/__init__.py
salesforce_api/services/bulk/base.py
salesforce_api/services/bulk/default.py
salesforce_api/services/bulk/v1.py
salesforce_api/services/bulk/v2.py
salesforce_api/utils/__init__.py
salesforce_api/utils/bulk.py
salesforce_api/utils/misc.py
salesforce_api/utils/retrieve.py
salesforce_api/utils/soap.py
tests/test_login.py
tests/test_service_basic.py
tests/test_service_bulk_v1.py
tests/test_service_bulk_v2.py
tests/test_service_deploy.py
tests/test_service_retrieve.py
tests/test_service_sobjects.py
tests/test_service_tooling.py