Metadata-Version: 2.4
Name: salesforce-api
Version: 0.1.46
Summary: Salesforce API wrapper
Home-page: https://github.com/felixlindstrom/python-salesforce-api
Author: Felix Lindstrom
Author-email: felix.lindstrom@gmail.com
License: MIT
Keywords: salesforce,salesforce api,salesforce bulk api
Classifier: Intended Audience :: Developers
Classifier: License :: OSI Approved :: MIT License
Classifier: Operating System :: OS Independent
Classifier: Programming Language :: Python
Classifier: Programming Language :: Python :: 3
Classifier: Topic :: Software Development :: Libraries :: Python Modules
License-File: LICENSE
Requires-Dist: requests
Requires-Dist: xmltodict
Requires-Dist: url-normalize
Dynamic: author
Dynamic: author-email
Dynamic: classifier
Dynamic: description
Dynamic: description-content-type
Dynamic: home-page
Dynamic: keywords
Dynamic: license
Dynamic: license-file
Dynamic: requires-dist
Dynamic: summary
